rtl.sv
// Code your design here
module full_adder_3bit (
    input  logic [2:0] a,
    input  logic [2:0] b,
    input  logic       cin,
    output logic [2:0] sum,
    output logic       cout
);
    // 1. Create a 4-bit internal variable to hold the full result
    logic [3:0] full_result;

    // 2. Perform the addition
    assign full_result = a + b + cin;

    // 3. Separate the outputs manually
    assign sum  = full_result[2:0]; // The lower 3 bits are the sum
    assign cout = full_result[3];   // The 4th bit (MSB) is the carry-out
    
endmodule

tb.sv
// Code your testbench here
// or browse Examples
class adder_transaction;
    // 3-bit inputs and 1-bit carry-in
    rand bit [2:0] a;
    rand bit [2:0] b;
    rand bit cin;
endclass

module full_adder_tb;
    // Signals to connect to the DUT
    logic [2:0] a, b, sum;
    logic cin, cout;

    // Instantiate the 3-bit Full Adder
    full_adder_3bit dut (
        .a(a),
        .b(b),
        .cin(cin),
        .sum(sum),
        .cout(cout)
    );

    // Coverage to ensure we test varied ranges
    covergroup cg;
        option.per_instance = 1;
        cp_a:   coverpoint a;
        cp_b:   coverpoint b;
        cp_cin: coverpoint cin;
        // Cross to ensure we test combinations that cause carry-out
        cross_all: cross cp_a, cp_b, cp_cin;
    endgroup

    initial begin
        adder_transaction trans = new();
        cg cov_inst = new();
        
        // EPWave setup
        $dumpfile("dump.vcd");
      $dumpvars(0, full_adder_tb);

        $display("Time\t A \t B \t Cin | Sum \t Cout");
        
        repeat (30) begin
            if (!trans.randomize()) $error("Randomization failed");
            
            // Apply randomized stimulus
            a = trans.a;
            b = trans.b;
            cin = trans.cin;
            
            #10; // Wait for logic to propagate

            // --- SEPARATE OUTPUT ASSERTION ---
            // We check the 3-bit sum and the 1-bit carry separately
            assert(sum  === ((a + b + cin) % 8)) else $error("Sum Mismatch!");
            assert(cout === ((a + b + cin) >= 8)) else $error("Carry Mismatch!");

            $display("%0t\t %d \t %d \t %b   | %d \t %b", $time, a, b, cin, sum, cout);
            cov_inst.sample();
        end

        $display("Final Functional Coverage: %.2f%%", cov_inst.get_inst_coverage());
        $finish;
    end
endmodule

dump.vcd
$date
Mon Feb 23 09:53:30 2026
$end
$version
Riviera-PRO Version 2025.04.139.9738
$end
$timescale
1 ns
$end

$scope module full_adder_tb $end
$var reg 3 ! a [2:0] $end
$var reg 3 " b [2:0] $end
$var reg 3 # sum [2:0] $end
$var reg 1 $ cin $end
$var reg 1 % cout $end

$scope module dut $end
$var wire 3 & a [2:0] $end
$var wire 3 ' b [2:0] $end
$var wire 1 ( cin $end
$var reg 3 ) sum [2:0] $end
$var reg 1 * cout $end
$var reg 4 + full_result [3:0] $end
$upscope $end

$upscope $end

$enddefinitions $end
$dumpvars
b10 !
b1 "
b100 #
1$
0%
b10 &
b1 '
1(
b100 )
0*
b100 +
$end
#10
b111 !
b111 "
0$
0(
b111 '
b111 &
b1110 +
b110 )
1*
b110 #
1%
#20
b11 !
b100 "
b100 '
b11 &
b111 +
b111 )
0*
b111 #
0%
#30
b101 !
b11 "
1$
1(
b11 '
b101 &
b1001 +
b1 )
1*
b1 #
1%
#40
b1 !
b0 "
b0 '
b1 &
b10 +
b10 )
0*
b10 #
0%
#50
b100 "
0$
0(
b100 '
b101 +
b101 )
b101 #
#70
b11 !
b101 "
b101 '
b11 &
b1000 +
b0 )
1*
b0 #
1%
#80
b101 !
b1 "
b1 '
b101 &
b110 +
b110 )
0*
b110 #
0%
#90
b100 !
b11 "
1$
1(
b11 '
b100 &
b1000 +
b0 )
1*
b0 #
1%
#100
b11 !
b111 "
b111 '
b11 &
b1011 +
b11 )
b11 #
#110
b110 !
b11 "
b11 '
b110 &
b1010 +
b10 )
b10 #
#120
b0 "
0$
0(
b0 '
b110 +
b110 )
0*
b110 #
0%
#130
1$
1(
b111 +
b111 )
b111 #
#140
b1 !
b1 "
b1 '
b1 &
b11 +
b11 )
b11 #
#150
b100 !
b100 "
0$
0(
b100 '
b100 &
b1000 +
b0 )
1*
b0 #
1%
#160
b10 !
b101 "
1$
1(
b101 '
b10 &
#170
b111 !
b11 "
0$
0(
b11 '
b111 &
b1010 +
b10 )
b10 #
#180
b101 !
b10 "
1$
1(
b10 '
b101 &
b1000 +
b0 )
b0 #
#190
b111 "
b111 '
b1101 +
b101 )
b101 #
#200
b0 !
b1 "
b1 '
b0 &
b10 +
b10 )
0*
b10 #
0%
#210
b100 !
b0 "
0$
0(
b0 '
b100 &
b100 +
b100 )
b100 #
#220
b0 !
b101 "
b101 '
b0 &
b101 +
b101 )
b101 #
#230
b110 !
b11 "
1$
1(
b11 '
b110 &
b1010 +
b10 )
1*
b10 #
1%
#240
b11 !
b1 "
b1 '
b11 &
b101 +
b101 )
0*
b101 #
0%
#250
b111 !
b101 "
0$
0(
b101 '
b111 &
b1100 +
b100 )
1*
b100 #
1%
#260
b100 "
b100 '
b1011 +
b11 )
b11 #
#270
b10 !
b11 "
1$
1(
b11 '
b10 &
b110 +
b110 )
0*
b110 #
0%
#280
b1 !
b0 "
b0 '
b1 &
b10 +
b10 )
b10 #
#290
b110 !
b101 "
b101 '
b110 &
b1100 +
b100 )
1*
b100 #
1%
